mongantic/__init__.py
mongantic-0.0.1.dist-info/METADATA
mongantic-0.0.1.dist-info/WHEEL
mongantic-0.0.1.dist-info/top_level.txt
mongantic-0.0.1.dist-info/RECORD
